<?xml version="1.0" encoding="UTF-8"?>
<metadata xml:lang="en"><Esri><CreaDate>20150915</CreaDate><CreaTime>14005600</CreaTime><ArcGISFormat>1.0</ArcGISFormat><SyncOnce>TRUE</SyncOnce><ModDate>20150916</ModDate><ModTime>102044</ModTime></Esri><dataIdInfo><idCitation><resTitle>Segmentation Tool</resTitle></idCitation></dataIdInfo><distInfo><distributor><distorFormat><formatName>ArcToolbox Tool</formatName></distorFormat></distributor></distInfo><tool name="SegmentationTool" displayname="Segmentation Tool" toolboxalias="GNAT"><parameters><param name="InputStreamNetwork" displayname="Input Stream Network" type="Required" direction="Input" datatype="Feature Layer" expression="InputStreamNetwork"/><param name="InputSegmentDistance" displayname="Segment Distance (Meters)" type="Required" direction="Input" datatype="Double" expression="InputSegmentDistance"/><param name="strRemainderRule" displayname="Rule for Remainders" type="Required" direction="Input" datatype="String" expression="Leave Remainder as Segment | Divide Remainder Proportionally"/><param name="fieldStreamName" displayname="Stream BranchID Field" type="Optional" direction="Input" datatype="String" expression="{fieldStreamName}"/><param name="fieldSegmentID" displayname="Output SegmentID Field" type="Required" direction="Input" datatype="String" expression="fieldSegmentID"/><param name="outputStreamOrderFC" displayname="Output Segmented Line Network" type="Required" direction="Output" datatype="Feature Class" expression="outputStreamOrderFC"/><param name="InputTempWorkspace" displayname="Scratch Workspace" type="Optional" direction="Input" datatype="Workspace" expression="{InputTempWorkspace}"/></parameters></tool></metadata>
